django_lit_urls/py.typed
django_lit_urls/serializer.py
django_lit_urls/serializer.pyi
django_lit_urls/templates/urls_map.js
django_lit_urls/utils.py
django_lit_urls/utils.pyi
django_lit_urls-0.1.4.dist-info/LICENSE
django_lit_urls-0.1.4.dist-info/METADATA
django_lit_urls-0.1.4.dist-info/WHEEL
django_lit_urls-0.1.4.dist-info/RECORD
