Metadata-Version: 2.1
Name: django_lit_urls
Version: 0.1.4
Summary: Django URLS delivered as string literal functions in Javascript
License: GPLv3
Author: Josh Brooks
Author-email: josh@catalpa.io
Requires-Python: >=3.8,<4.0
Classifier: License :: Other/Proprietary License
Classifier: Programming Language :: Python :: 3
Classifier: Programming Language :: Python :: 3.8
Classifier: Programming Language :: Python :: 3.9
Classifier: Programming Language :: Python :: 3.10
Classifier: Programming Language :: Python :: 3.11
Classifier: Programming Language :: Python :: 3.12
Requires-Dist: Django (>3.1)
Requires-Dist: pydantic (>=1.9,<3)
